polars_bloomberg/__init__.py
polars_bloomberg/plbbg.py
polars_bloomberg/py.typed
polars_bloomberg-0.5.4.dist-info/licenses/LICENSE
polars_bloomberg-0.5.4.dist-info/METADATA
polars_bloomberg-0.5.4.dist-info/WHEEL
polars_bloomberg-0.5.4.dist-info/top_level.txt
polars_bloomberg-0.5.4.dist-info/RECORD
