Metadata-Version: 2.4
Name: polars-bloomberg
Version: 0.5.4
Summary: Python library providing a Polars DataFrame interface for easy and intuitive access to Bloomberg API.
Author: Marek Ozana, Ph.D.
License-Expression: Apache-2.0
Project-URL: Homepage, https://github.com/MarekOzana/polars-bloomberg
Project-URL: Documentation, https://marekozana.github.io/polars-bloomberg
Classifier: Development Status :: 4 - Beta
Classifier: Intended Audience :: Developers
Classifier: Intended Audience :: Financial and Insurance Industry
Classifier: Topic :: Software Development :: Libraries
Classifier: Topic :: Office/Business :: Financial
Classifier: Programming Language :: Python :: 3
Classifier: Programming Language :: Python :: 3.12
Classifier: Programming Language :: Python :: 3.13
Classifier: Programming Language :: Python :: 3.14
Classifier: Operating System :: OS Independent
Requires-Python: >=3.12
License-File: LICENSE
Requires-Dist: polars>=1.7.1
Requires-Dist: blpapi>=3.24.0
Provides-Extra: dev
Requires-Dist: pytest; extra == "dev"
Requires-Dist: pytest-cov; extra == "dev"
Requires-Dist: jupyter; extra == "dev"
Requires-Dist: altair; extra == "dev"
Requires-Dist: nox; extra == "dev"
Requires-Dist: pyyaml; extra == "dev"
Requires-Dist: vl-convert-python; extra == "dev"
Requires-Dist: ruff>=0.14.10; extra == "dev"
Provides-Extra: docs
Requires-Dist: mkdocs>=1.5.0; extra == "docs"
Requires-Dist: mkdocstrings[python]>=0.22.0; extra == "docs"
Requires-Dist: mkdocs-jupyter; extra == "docs"
Requires-Dist: great_tables; extra == "docs"
Requires-Dist: mkdocs-material>=9.7.0; extra == "docs"
Dynamic: license-file
